pypetb/__init__.py
pypetb/Capability.py
pypetb/Repeatability.py
pypetb/RnR.py
pypetb/tables.py
pypetb-1.0.0.dist-info/LICENSE.txt
pypetb-1.0.0.dist-info/METADATA
pypetb-1.0.0.dist-info/WHEEL
pypetb-1.0.0.dist-info/RECORD
