Metadata-Version: 2.3
Name: pypetb
Version: 1.0.0
Summary: A Set of process engineering tools. Gage RnR, Automated Gage repeatability and Capability analysis are currently available
License: MIT
Keywords: engineering,chemical engineering,six sigma,process improvement
Author: Jose Garcia
Author-email: jgherruzo@gmail.com
Requires-Python: >=3.11,<4.0
Classifier: Framework :: Flake8
Classifier: Framework :: Matplotlib
Classifier: Framework :: Pytest
Classifier: Framework :: Sphinx
Classifier: Intended Audience :: Manufacturing
Classifier: License :: OSI Approved :: MIT License
Classifier: Programming Language :: Python :: 3
Classifier: Programming Language :: Python :: 3.11
Classifier: Programming Language :: Python :: 3.12
Classifier: Programming Language :: Python :: 3.13
Classifier: Topic :: Scientific/Engineering :: Chemistry
Requires-Dist: Jinja2 (>=3.1.6,<4.0.0)
Requires-Dist: Pillow (>=10.3.0)
Requires-Dist: Tornado (>=6.5.0,<7.0.0)
Requires-Dist: matplotlib (>=3.8.2,<4.0.0) ; python_version == "3.11"
Requires-Dist: numpy (>=1.26.2,<2.0.0) ; python_version == "3.11"
Requires-Dist: pandas (>=2.1.4,<3.0.0) ; python_version == "3.11"
Requires-Dist: requests (>=2.32.4,<3.0.0)
Requires-Dist: scipy (>=1.11.4,<2.0.0) ; python_version == "3.11"
Requires-Dist: seaborn (>=0.13.0,<0.14.0) ; python_version == "3.11"
Requires-Dist: urllib3 (>=2.5.0,<3.0.0)
Project-URL: Documentation, https://pypetb.readthedocs.io/en/latest/
Project-URL: Repository, https://github.com/jgherruzo/pyPETB
